muffin_redis/__init__.py
muffin_redis/py.typed
muffin_redis-3.9.0.dist-info/METADATA
muffin_redis-3.9.0.dist-info/WHEEL
muffin_redis-3.9.0.dist-info/RECORD
