Metadata-Version: 2.3
Name: muffin-redis
Version: 3.9.0
Summary: Redis support for Muffin framework.
License: MIT
Keywords: redis,muffin,asgi,asyncio
Author: Kirill Klenov
Author-email: horneds@gmail.com
Requires-Python: >=3.10,<4.0
Classifier: Development Status :: 5 - Production/Stable
Classifier: Framework :: AsyncIO
Classifier: Intended Audience :: Developers
Classifier: License :: OSI Approved :: MIT License
Classifier: Programming Language :: Python
Classifier: Programming Language :: Python :: 3
Classifier: Programming Language :: Python :: 3.10
Classifier: Programming Language :: Python :: 3.11
Classifier: Programming Language :: Python :: 3.12
Classifier: Programming Language :: Python :: 3.13
Provides-Extra: redislite
Requires-Dist: muffin
Requires-Dist: redis
Requires-Dist: redislite ; extra == "redislite"
Project-URL: Homepage, https://github.com/klen/muffin-redis
Project-URL: Repository, https://github.com/klen/muffin-redis
